{
  "totals": {
    "bytes": 2121827,
    "count": 44,
    "byHost": {
      "floodmap.drose.io": 1521811,
      "unpkg.com": 222058,
      "static.cloudflareinsights.com": 7119,
      "": 370839
    },
    "byType": {
      "text": 14370,
      "json": 437,
      "js": 599197,
      "binary": 568886,
      "pbf": 938937
    }
  },
  "tiles": {
    "elevation": {
      "totalBytes": 568886,
      "totalCount": 25,
      "totalTime": 5370.589,
      "avgTime": 214.82356,
      "maxTime": 469.47700000000003,
      "byZoom": {
        "9": {
          "bytes": 568886,
          "count": 25,
          "totalTime": 5370.589,
          "avgTime": 214.82356,
          "maxTime": 469.47700000000003
        }
      },
      "encodings": [
        "br"
      ],
      "caches": [
        "public, max-age=31536000, immutable"
      ]
    },
    "vector": {
      "totalBytes": 938937,
      "totalCount": 9,
      "totalTime": 4607.932,
      "avgTime": 511.9924444444444,
      "maxTime": 656.18,
      "byZoom": {
        "8": {
          "bytes": 938937,
          "count": 9,
          "totalTime": 4607.932,
          "avgTime": 511.9924444444444,
          "maxTime": 656.18
        }
      },
      "encodings": [
        "br"
      ],
      "caches": [
        "public, max-age=31536000, immutable"
      ]
    }
  },
  "largest": [
    {
      "url": "blob:https://floodmap.drose.io/9b53be5e-ab28-469f-9b1d-fb2dba63cf10",
      "bytes": 370839,
      "status": 200,
      "type": "js"
    },
    {
      "url": "https://unpkg.com/maplibre-gl@4.7.1/dist/maplibre-gl.js",
      "bytes": 212369,
      "status": 200,
      "type": "js"
    },
    {
      "url": "https://floodmap.drose.io/api/v1/tiles/vector/usa/8/69/106.pbf",
      "bytes": 206688,
      "status": 200,
      "type": "pbf"
    },
    {
      "url": "https://floodmap.drose.io/api/v1/tiles/vector/usa/8/69/107.pbf",
      "bytes": 195673,
      "status": 200,
      "type": "pbf"
    },
    {
      "url": "https://floodmap.drose.io/api/v1/tiles/vector/usa/8/70/107.pbf",
      "bytes": 168507,
      "status": 200,
      "type": "pbf"
    },
    {
      "url": "https://floodmap.drose.io/api/v1/tiles/vector/usa/8/70/106.pbf",
      "bytes": 130233,
      "status": 200,
      "type": "pbf"
    },
    {
      "url": "https://floodmap.drose.io/api/v1/tiles/vector/usa/8/70/108.pbf",
      "bytes": 112205,
      "status": 200,
      "type": "pbf"
    },
    {
      "url": "https://floodmap.drose.io/api/v1/tiles/vector/usa/8/69/108.pbf",
      "bytes": 84691,
      "status": 200,
      "type": "pbf"
    },
    {
      "url": "https://floodmap.drose.io/api/v1/tiles/elevation-data/9/139/212.u16",
      "bytes": 51236,
      "status": 200,
      "type": "binary"
    },
    {
      "url": "https://floodmap.drose.io/api/v1/tiles/elevation-data/9/139/213.u16",
      "bytes": 48553,
      "status": 200,
      "type": "binary"
    },
    {
      "url": "https://floodmap.drose.io/api/v1/tiles/elevation-data/9/139/214.u16",
      "bytes": 47785,
      "status": 200,
      "type": "binary"
    },
    {
      "url": "https://floodmap.drose.io/api/v1/tiles/elevation-data/9/140/213.u16",
      "bytes": 46889,
      "status": 200,
      "type": "binary"
    },
    {
      "url": "https://floodmap.drose.io/api/v1/tiles/elevation-data/9/138/212.u16",
      "bytes": 45098,
      "status": 200,
      "type": "binary"
    },
    {
      "url": "https://floodmap.drose.io/api/v1/tiles/elevation-data/9/140/214.u16",
      "bytes": 41413,
      "status": 200,
      "type": "binary"
    },
    {
      "url": "https://floodmap.drose.io/api/v1/tiles/elevation-data/9/140/215.u16",
      "bytes": 40318,
      "status": 200,
      "type": "binary"
    },
    {
      "url": "https://floodmap.drose.io/api/v1/tiles/elevation-data/9/139/215.u16",
      "bytes": 39045,
      "status": 200,
      "type": "binary"
    },
    {
      "url": "https://floodmap.drose.io/api/v1/tiles/elevation-data/9/140/212.u16",
      "bytes": 37977,
      "status": 200,
      "type": "binary"
    },
    {
      "url": "https://floodmap.drose.io/api/v1/tiles/elevation-data/9/138/213.u16",
      "bytes": 35139,
      "status": 200,
      "type": "binary"
    },
    {
      "url": "https://floodmap.drose.io/api/v1/tiles/elevation-data/9/138/214.u16",
      "bytes": 32363,
      "status": 200,
      "type": "binary"
    },
    {
      "url": "https://floodmap.drose.io/api/v1/tiles/elevation-data/9/140/216.u16",
      "bytes": 32339,
      "status": 200,
      "type": "binary"
    },
    {
      "url": "https://floodmap.drose.io/api/v1/tiles/elevation-data/9/139/216.u16",
      "bytes": 31355,
      "status": 200,
      "type": "binary"
    },
    {
      "url": "https://floodmap.drose.io/api/v1/tiles/vector/usa/8/68/106.pbf",
      "bytes": 31109,
      "status": 200,
      "type": "pbf"
    },
    {
      "url": "https://floodmap.drose.io/api/v1/tiles/elevation-data/9/138/215.u16",
      "bytes": 20130,
      "status": 200,
      "type": "binary"
    },
    {
      "url": "https://floodmap.drose.io/api/v1/tiles/elevation-data/9/137/212.u16",
      "bytes": 10998,
      "status": 200,
      "type": "binary"
    },
    {
      "url": "https://unpkg.com/maplibre-gl@4.7.1/dist/maplibre-gl.css",
      "bytes": 9689,
      "status": 200,
      "type": "text"
    }
  ],
  "pageTimings": {
    "onContentLoad": 1007,
    "onLoad": 1032
  }
}
